arctic_tern/__init__.py
arctic_tern/_migrate_asyncpg.py
arctic_tern/_migrate_psycopg.py
arctic_tern/filename.py
arctic_tern-0.2.0.dist-info/LICENSE
arctic_tern-0.2.0.dist-info/WHEEL
arctic_tern-0.2.0.dist-info/METADATA
arctic_tern-0.2.0.dist-info/RECORD
