Metadata-Version: 2.1
Name: arctic-tern
Version: 0.2.0
Summary: SQL migrations for python and postgres
Home-page: https://github.com/ConvergysLabs/arctic-tern
License: MIT
Author: Eric Grunzke
Author-email: eric@grunzke.com
Requires-Python: >=3.8,<4.0
Classifier: License :: OSI Approved :: MIT License
Classifier: Programming Language :: Python :: 3
Classifier: Programming Language :: Python :: 3.8
Provides-Extra: asyncpg
Provides-Extra: psycopg
Requires-Dist: asyncpg (>=0.20.1,<0.21.0); extra == "asyncpg"
Requires-Dist: psycopg2 (>=2.7,<3.0); extra == "psycopg"
